{
  "annotations": {
    "list": [
      {
        "builtIn": 1,
        "datasource": "-- Grafana --",
        "enable": true,
        "hide": true,
        "iconColor": "rgba(0, 211, 255, 1)",
        "name": "Annotations & Alerts",
        "type": "dashboard"
      }
    ]
  },
  "description": "No. Agbots",
  "editable": true,
  "gnetId": null,
  "graphTooltip": 0,
  "id": 10,
  "links": [],
  "panels": [
    {
      "aliasColors": {},
      "bars": false,
      "dashLength": 10,
      "dashes": false,
      "datasource": "Prometheus",
      "description": "No. Agbots",
      "fill": 1,
      "fillGradient": 0,
      "gridPos": {
        "h": 8,
        "w": 12,
        "x": 0,
        "y": 0
      },
      "hiddenSeries": false,
      "id": 4,
      "legend": {
        "avg": false,
        "current": false,
        "max": false,
        "min": false,
        "show": true,
        "total": false,
        "values": false
      },
      "lines": true,
      "linewidth": 1,
      "nullPointMode": "null",
      "options": {
        "dataLinks": []
      },
      "percentage": false,
      "pointradius": 2,
      "points": false,
      "renderer": "flot",
      "seriesOverrides": [],
      "spaceLength": 10,
      "stack": false,
      "steppedLine": false,
      "targets": [
        {
          "expr": "agbot_partitions_count",
          "instant": false,
          "legendFormat": "No. Agbot",
          "refId": "A"
        }
      ],
      "thresholds": [],
      "timeFrom": null,
      "timeRegions": [],
      "timeShift": null,
      "title": "Partitions - Agbots",
      "tooltip": {
        "shared": true,
        "sort": 0,
        "value_type": "individual"
      },
      "type": "graph",
      "xaxis": {
        "buckets": null,
        "mode": "time",
        "name": null,
        "show": true,
        "values": []
      },
      "yaxes": [
        {
          "decimals": 0,
          "format": "short",
          "label": "No. Agbots",
          "logBase": 1,
          "max": null,
          "min": null,
          "show": true
        },
        {
          "format": "short",
          "label": null,
          "logBase": 1,
          "max": null,
          "min": null,
          "show": true
        }
      ],
      "yaxis": {
        "align": false,
        "alignLevel": null
      }
    },
    {
      "columns": [],
      "datasource": "Prometheus",
      "description": "Agbot Hearbeat",
      "fontSize": "100%",
      "gridPos": {
        "h": 8,
        "w": 12,
        "x": 12,
        "y": 0
      },
      "id": 6,
      "options": {},
      "pageSize": null,
      "pluginVersion": "6.6.1",
      "showHeader": true,
      "sort": {
        "col": 0,
        "desc": true
      },
      "styles": [
        {
          "alias": "Time",
          "align": "auto",
          "dateFormat": "YYYY-MM-DD HH:mm:ss",
          "pattern": "Time",
          "type": "date"
        },
        {
          "alias": "",
          "align": "right",
          "colorMode": null,
          "colors": [
            "rgba(245, 54, 54, 0.9)",
            "rgba(237, 129, 40, 0.89)",
            "rgba(50, 172, 45, 0.97)"
          ],
          "decimals": 2,
          "pattern": "heartbeat",
          "thresholds": [],
          "type": "hidden",
          "unit": "dateTimeAsUS"
        },
        {
          "alias": "",
          "align": "auto",
          "colorMode": null,
          "colors": [
            "rgba(245, 54, 54, 0.9)",
            "rgba(237, 129, 40, 0.89)",
            "rgba(50, 172, 45, 0.97)"
          ],
          "dateFormat": "YYYY-MM-DD HH:mm:ss",
          "decimals": 2,
          "mappingType": 1,
          "pattern": "instance",
          "thresholds": [],
          "type": "hidden",
          "unit": "short"
        },
        {
          "alias": "",
          "align": "auto",
          "colorMode": null,
          "colors": [
            "rgba(245, 54, 54, 0.9)",
            "rgba(237, 129, 40, 0.89)",
            "rgba(50, 172, 45, 0.97)"
          ],
          "dateFormat": "YYYY-MM-DD HH:mm:ss",
          "decimals": 2,
          "mappingType": 1,
          "pattern": "__name__",
          "thresholds": [],
          "type": "hidden",
          "unit": "short"
        },
        {
          "alias": "",
          "align": "auto",
          "colorMode": null,
          "colors": [
            "rgba(245, 54, 54, 0.9)",
            "rgba(237, 129, 40, 0.89)",
            "rgba(50, 172, 45, 0.97)"
          ],
          "dateFormat": "YYYY-MM-DD HH:mm:ss",
          "decimals": 2,
          "mappingType": 1,
          "pattern": "job",
          "thresholds": [],
          "type": "hidden",
          "unit": "short"
        },
        {
          "alias": "",
          "align": "auto",
          "colorMode": null,
          "colors": [
            "rgba(245, 54, 54, 0.9)",
            "rgba(237, 129, 40, 0.89)",
            "rgba(50, 172, 45, 0.97)"
          ],
          "dateFormat": "YYYY-MM-DD HH:mm:ss",
          "decimals": 2,
          "mappingType": 1,
          "pattern": "partitions_id",
          "thresholds": [],
          "type": "hidden",
          "unit": "short"
        },
        {
          "alias": "",
          "align": "auto",
          "colorMode": null,
          "colors": [
            "rgba(245, 54, 54, 0.9)",
            "rgba(237, 129, 40, 0.89)",
            "rgba(50, 172, 45, 0.97)"
          ],
          "dateFormat": "YYYY-MM-DD HH:mm:ss",
          "decimals": 2,
          "mappingType": 1,
          "pattern": "partitions_owner",
          "thresholds": [],
          "type": "hidden",
          "unit": "short"
        },
        {
          "alias": "Heartbeat",
          "align": "auto",
          "colorMode": null,
          "colors": [
            "rgba(245, 54, 54, 0.9)",
            "rgba(237, 129, 40, 0.89)",
            "rgba(50, 172, 45, 0.97)"
          ],
          "dateFormat": "YYYY-MM-DD HH:mm:ss",
          "decimals": 2,
          "mappingType": 1,
          "pattern": "Value",
          "thresholds": [],
          "type": "number",
          "unit": "dateTimeAsUS"
        }
      ],
      "targets": [
        {
          "expr": "agbot_partitions*1000",
          "format": "table",
          "instant": true,
          "refId": "A"
        }
      ],
      "timeFrom": null,
      "timeShift": null,
      "title": "Agbot",
      "transform": "table",
      "type": "table"
    },
    {
      "columns": [],
      "datasource": "Prometheus",
      "fontSize": "100%",
      "gridPos": {
        "h": 10,
        "w": 24,
        "x": 0,
        "y": 8
      },
      "id": 2,
      "options": {},
      "pageSize": null,
      "showHeader": true,
      "sort": {
        "col": 0,
        "desc": true
      },
      "styles": [
        {
          "alias": "Time",
          "align": "auto",
          "dateFormat": "YYYY-MM-DD HH:mm:ss",
          "pattern": "Time",
          "type": "date"
        },
        {
          "alias": "",
          "align": "auto",
          "colorMode": null,
          "colors": [
            "rgba(245, 54, 54, 0.9)",
            "rgba(237, 129, 40, 0.89)",
            "rgba(50, 172, 45, 0.97)"
          ],
          "dateFormat": "YYYY-MM-DD HH:mm:ss",
          "decimals": 2,
          "mappingType": 1,
          "pattern": "__name__",
          "thresholds": [],
          "type": "hidden",
          "unit": "short"
        },
        {
          "alias": "",
          "align": "auto",
          "colorMode": null,
          "colors": [
            "rgba(245, 54, 54, 0.9)",
            "rgba(237, 129, 40, 0.89)",
            "rgba(50, 172, 45, 0.97)"
          ],
          "dateFormat": "YYYY-MM-DD HH:mm:ss",
          "decimals": 2,
          "mappingType": 1,
          "pattern": "instance",
          "thresholds": [],
          "type": "hidden",
          "unit": "short"
        },
        {
          "alias": "",
          "align": "auto",
          "colorMode": null,
          "colors": [
            "rgba(245, 54, 54, 0.9)",
            "rgba(237, 129, 40, 0.89)",
            "rgba(50, 172, 45, 0.97)"
          ],
          "dateFormat": "YYYY-MM-DD HH:mm:ss",
          "decimals": 2,
          "mappingType": 1,
          "pattern": "job",
          "thresholds": [],
          "type": "hidden",
          "unit": "short"
        },
        {
          "alias": "Heartbeat",
          "align": "auto",
          "colorMode": null,
          "colors": [
            "rgba(245, 54, 54, 0.9)",
            "rgba(237, 129, 40, 0.89)",
            "rgba(50, 172, 45, 0.97)"
          ],
          "dateFormat": "MM/DD/YY h:mm:ss a",
          "decimals": 2,
          "mappingType": 1,
          "pattern": "Value",
          "thresholds": [],
          "type": "number",
          "unit": "dateTimeAsUS"
        },
        {
          "alias": "",
          "align": "auto",
          "colorMode": null,
          "colors": [
            "rgba(245, 54, 54, 0.9)",
            "rgba(237, 129, 40, 0.89)",
            "rgba(50, 172, 45, 0.97)"
          ],
          "dateFormat": "YYYY-MM-DD HH:mm:ss",
          "decimals": 2,
          "mappingType": 1,
          "pattern": "partitions_heartbeat",
          "thresholds": [],
          "type": "hidden",
          "unit": "short"
        },
        {
          "alias": "",
          "align": "auto",
          "colorMode": null,
          "colors": [
            "rgba(245, 54, 54, 0.9)",
            "rgba(237, 129, 40, 0.89)",
            "rgba(50, 172, 45, 0.97)"
          ],
          "dateFormat": "YYYY-MM-DD HH:mm:ss",
          "decimals": 2,
          "mappingType": 1,
          "pattern": "heartbeat",
          "thresholds": [],
          "type": "hidden",
          "unit": "short"
        },
        {
          "alias": "Partition ID",
          "align": "auto",
          "colorMode": null,
          "colors": [
            "rgba(245, 54, 54, 0.9)",
            "rgba(237, 129, 40, 0.89)",
            "rgba(50, 172, 45, 0.97)"
          ],
          "dateFormat": "YYYY-MM-DD HH:mm:ss",
          "decimals": 0,
          "mappingType": 1,
          "pattern": "partitions_id",
          "thresholds": [],
          "type": "number",
          "unit": "short"
        },
        {
          "alias": "Partition Owner",
          "align": "auto",
          "colorMode": null,
          "colors": [
            "rgba(245, 54, 54, 0.9)",
            "rgba(237, 129, 40, 0.89)",
            "rgba(50, 172, 45, 0.97)"
          ],
          "dateFormat": "YYYY-MM-DD HH:mm:ss",
          "decimals": 2,
          "mappingType": 1,
          "pattern": "partitions_owner",
          "thresholds": [],
          "type": "number",
          "unit": "short"
        }
      ],
      "targets": [
        {
          "expr": "agbot_partitions*1000",
          "format": "table",
          "instant": true,
          "refId": "A"
        }
      ],
      "timeFrom": null,
      "timeShift": null,
      "title": "Partitions",
      "transform": "table",
      "type": "table"
    }
  ],
  "refresh": false,
  "schemaVersion": 22,
  "style": "dark",
  "tags": [],
  "templating": {
    "list": []
  },
  "time": {
    "from": "now-6h",
    "to": "now"
  },
  "timepicker": {
    "refresh_intervals": [
      "5s",
      "10s",
      "30s",
      "1m",
      "5m",
      "15m",
      "30m",
      "1h",
      "2h",
      "1d"
    ]
  },
  "timezone": "",
  "title": "Partitions-Agbots",
  "uid": "l16HExwZk",
  "version": 10
}